{"citationID":"YCSHBEPQ","properties":{"formattedCitation":"\\super [1]\\nosupersub{}","plainCitation":"[1]","noteIndex":0},"citationItems":[{"id":469,"uris":["http://zotero.org/users/12887004/items/E78S579E"],"itemData":{"id":469,"type":"book","title":"</w:instrText></w:r><w:r w:rsidR="0092793D" w:rsidRPr="00E7551E"><w:rPr><w:rFonts w:cs="Times New Roman"/><w:lang w:eastAsia="zh-CN"/></w:rPr><w:instrText>中华人民共和国国家统计局</w:instrText></w:r><w:r w:rsidR="0092793D" w:rsidRPr="00E7551E"><w:rPr><w:rFonts w:cs="Times New Roman"/><w:lang w:eastAsia="zh-CN"/></w:rPr><w:instrText xml:space="preserve">. 2023 </w:instrText></w:r><w:r w:rsidR="0092793D" w:rsidRPr="00E7551E"><w:rPr><w:rFonts w:cs="Times New Roman"/><w:lang w:eastAsia="zh-CN"/></w:rPr><w:instrText>中国统计年鉴</w:instrText></w:r><w:r w:rsidR="0092793D" w:rsidRPr="00E7551E"><w:rPr><w:rFonts w:cs="Times New Roman"/><w:lang w:eastAsia="zh-CN"/></w:rPr><w:instrText xml:space="preserve">[M]. </w:instrText></w:r><w:r w:rsidR="0092793D" w:rsidRPr="00E7551E"><w:rPr><w:rFonts w:cs="Times New Roman"/><w:lang w:eastAsia="zh-CN"/></w:rPr><w:instrText>北京：中国统计出版，</w:instrText></w:r><w:r w:rsidR="0092793D" w:rsidRPr="00E7551E"><w:rPr><w:rFonts w:cs="Times New Roman"/><w:lang w:eastAsia="zh-CN"/></w:rPr><w:instrText xml:space="preserve">2023."}}],"schema":"https://github.com/citation-style-language/schema/raw/master/csl-citation.json"}